<!DOCTYPE frameset SYSTEM "frameset.dtd">
<frameset>
  <predicate lemma="сойти">
    <note>NOTES: Added for LORELEI to support aligning RU and EN texts. Data from Skatje Myers unless otherwise noted.</note>
    <roleset id="сойти.01" name="go down, step down, come down, get down, dismount, descend	 ">
      <aliases>
	  <alias framenet="" pos="v" verbnet="">сходить</alias>
	  <alias framenet="" pos="n" verbnet="">схождение</alias>
	  <alias framenet="" pos="n" verbnet="">сход</alias>
      </aliases>
	  <note>сойти.01 NOTES: Roleset based on English verb frame descend.01</note>
	  <note>Corresponds to FrameBank senses 1,3,4</note>
      <roles>
        <role descr="entity in motion/goer" f="PPT" n="1"/>
		<role descr="extent" f="EXT" n="2"/>
		<role descr="start point, high point" f="DIR" n="3"/>
		<role descr="end point, low point" f="GOL" n="4"/>
      </roles>
      <example name="descend" src="Russian National Corpus[Сати Спивакова. Не всё (2002)] " type="">
        <text>Папа тогда ответил: "Вот и оставайтесь на небесах, а я сойду на землю".</text>
		<arg f="" n="1">я</arg>
		<rel f="">сойду</rel>
		<arg f="" n="4">на землю</arg>
      </example>
	  <example name="walk down" src="Russian National Corpus[Олег Тихомиров. Подвиг Магеллана // «Мурзилка», 2002]" type="">
        <text>По скрипучему трапу на берег сошли восемнадцать моряков.</text>
		<arg f="" n="3">По скрипучему трапу</arg>
		<arg f="" n="4">на берег</arg>
        <rel f="">сошли</rel>
		<arg f="" n="1">восемнадцать моряков</arg>
      </example>
	  <example name="came down off" src="Russian National Corpus [Польша -- добрая соседка: здесь примут по-домашнему! // «Даша», 2004] " type="">
        <text>В каждом доме есть магазинчики или рестораны, а сами они как будто сошли с ярких миниатюр.</text>
		<arg f="" n="1">сами они</arg>
		<arg f="adv" n="m">как будто</arg>
		<rel f="">сошли</rel>
		<arg f="" n="3">с ярких миниатюр</arg>
      </example>
    </roleset>
    
	<roleset id="сойти.02" name="step off, move off, come off, turn off from, derail, disappear, melt off, peel off">
      <aliases>
		<alias framenet="" pos="v" verbnet="">сходить</alias>
      </aliases>
	  <note>сойти.02 NOTES: Roleset based on English verb frame go.01</note>
	  <note>Corresponds to FrameBank senses 5,6,9</note>
      <roles>
		<role descr="entity in motion/goer" f="PPT" n="1"/>
		<role descr="extent" f="EXT" n="2"/>
		<role descr="start point" f="DIR" n="3"/>
		<role descr="end point, end state of arg1" f="GOL" n="4"/>
      </roles>
	  <example name="melt" src="Russian National Corpus[Весенний призыв (2004) // «Экран и сцена», 2004.05.06]" type="">
        <text>Пройдут дожди, сойдут снега… ".</text>
		<rel f="">сойдут</rel>
		<arg f="" n="1">снега</arg>
	  </example>
	  <example name="step off" src="Russian National Corpus[Василь Быков. Болото (2001)]" type="">
        <text>Что― всё равно, он не объяснил, сошёл с дороги в кустарник, пробрался через колючую чащобу и первым опустился, где стоял ― на повлажневшую от росы траву.</text>
		<rel f="">сошёл</rel>
		<arg f="" n="3">с дороги</arg>
		<arg f="" n="4">в кустарник</arg>
	  </example>
	  <example name="move" src="Russian National Corpus[Павел Кузнецов. Русский Феникс, или Что такое философия в России // «Звезда», 2001]" type="">
        <text>Запад есть Запад, Восток есть Восток, и с места они не сойдут…</text>
		<arg f="" n="3">с места</arg>
		<arg f="" n="1">они</arg>
		<arg f="neg" n="m">не</arg>
		<rel f="">сойдут</rel>
	  </example>
	</roleset>
	
	<roleset id="сойти.03" name="disembark, get off at a transport stop">
      <aliases>
	  <alias framenet="" pos="v" verbnet="">сходить</alias>
      </aliases>
	  <note>сойти.03 NOTES: Roleset based on English verb frame disembark.01</note>
	  <note>Corresponds to FrameBank sense 2</note>
	  <roles>
		<role descr="passenger(s)" f="PPT" n="0"/>
		<role descr="vehicle(s)" f="LOC" n="1"/>
      </roles>
	  <example name="debark" src="Russian National Corpus [Героиновый тюремщик (2003) // «Криминальная хроника», 2003.07.24] " type="">
        <text>Сойдя с поезда, Юрий прогулялся по вокзалу, а затем двинул в автоматическую камеру хранения.</text>
		<rel f="">Сойдя</rel>
		<arg f="" n="1">с поезда</arg>
	  </example>
	</roleset>
  
	<roleset id="сойти.04" name="stop a run (of a show, movie, act), stop showing, lose popularity, be not 'in'">
	  <aliases>
		<alias framenet="" pos="v" verbnet="">сходить</alias>
      </aliases>
	  <note>сойти.04 NOTES:Roleset based on English verb frame ran.09</note>
	  <note>ran.09-only negative or past, completive aspect!<note>
      <roles>
		<role descr="advertisement, series, etc" f="PPT" n="0"/>
		<role descr="medium " f="MNR" n="1"/>
	  </roles>
	  <note>English Arg0-PAG has no match in Russian frame</note>
	  <example name="quit acting" src="" type="Russian National Corpus[Я был когда-то странным... – беседа с национальным героем // «Пятое измерение», 2002]">
        <text>Когда я сошел с больших экранов, журналисты меня какое-то время доставали, пытались развести на скандал ― не получилось.</text>
		<arg f="tmp" n="m">Когда</arg>
		<arg f="" n="1">я</arg>
		<rel f="">сошел</rel>
		<arg f="" n="2">с больших экранов</arg>
	  </example>
	  <example name="stopped showing movies" src="" type="Russian National Corpus[Юрий Никулин. Мое любимое кино (1979)]">
        <text>Ко времени моих самостоятельных посещений кино его ранние фильмы уже сошли с экрана.</text>
		<arg f="tmp" n="m">Ко времени моих самостоятельных посещений кино</arg>
		<arg f="" n="1">его ранние фильмы</arg>
		<arg f="tmp" n="m">уже</arg>
		<rel f="">сошли</rel>
		<arg f="" n="2">с экрана</arg>
	  </example>
	</roleset>
	  
	<roleset id="сойти.05" name="pass as, be accepted as">
	  <aliases>
		<alias framenet="" pos="v" verbnet="">сходить</alias>
      </aliases>
	  <note>сойти.05 NOTES: Roleset based on English verb frame pass.06</note>
	  <note>Corresponds to FrameBank sense 8</note>
      <roles>
		<role descr="thing passing" f="PPT" n="1"/>
		<role descr="attributive" f="PRD" n="2"/>
		</roles>
	  <example name="" src="" type="Russian National Corpus[Олег Павлов. Карагандинские девятины, или Повесть последних дней // «Октябрь», 2001]">
        <text>Измученный и ограбленный вид арестанта, что сам бы мог сойти за жертву какого-нибудь преступления, нисколько её не смущал.</text>
		<arg f="" n="1">сам</arg>
		<rel f="">сойти</rel>
		<arg f="" n="2">за жертву какого-нибудь преступления</arg>
	  </example>
	</roleset>
  
	<roleset id="сойти.06" name="come to, turn out, pass, end up as.">
	  <aliases>
		<alias framenet="" pos="v" verbnet="">сходить</alias>
      </aliases>
	  <note>сойти.06 NOTES:Roleset based on English verb frame turn_out.11</note>
	  <note>Corresponds to FrameBank sense 7</note>
      <roles>
		<role descr="thing seeming" f="PPT" n="1"/>
		<role descr="attribute" f="PRD" n="2"/>
	  </roles>
	  <example name="come to nothing" src="" type="Russian National Corpus[Павел Иванов. Ключ к правовой экономике. Популярные хроники непопулярного закона // «Воздушно-космическая оборона», 2003]">
        <text>Правда, интерес к техническому регулированию сошёл на нет задолго до дня принятия закона ― 15 декабря 2002 г.</text>
		<arg f="dis" n="m">Правда</arg>
		<arg f="" n="1">интерес к техническому регулированию</arg>
		<rel f="">сошёл</rel>
		<arg f="" n="2">на нет</arg>
		<arg f="tmp" n="m">задолго до дня принятия закона ― 15 декабря 2002 г.</arg>
	  </example>
	</roleset>
  </predicate>

  <predicate>
	<roleset id="сойтись.07" name="meet, run into each other, come together, physically converge, meet, intersect, join for battle, approach mathematical limit for an integral, agree, be united, be similar, be consistent, concur, coincide, jibe.">
	  <aliases>
		<alias framenet="" pos="v" verbnet="">сходиться</alias>
		<alias framenet="" pos="v" verbnet="">схождение</alias>
      </aliases>
	  <note>Corresponds to FrameBank sense -ся 1,2,3-6; -ся 9-10</note>
	  <note>сойти.04 NOTES:Roleset based on English verb frame converge.01</note>
      <roles>
		<role descr="first (or all, in plural mention) things converging" f="PPT" n="0"/>
		<role descr="Other converger, converged-with" f="PPT" n="1"/>
		<role descr="Thing converged-on, often a topic of agreement)" f="GOL" n="2"/>
		</roles>
	  <example name="arg 0 and 1" src="" type="Russian National Corpus[Наталья Игрунова. Падение по горизонтали. Журнальное обозрение (2002) // «Известия», 2002.04.09]">
        <text>Отголоски темы ― в номере февральском, на страницах которого сошлись роман классический и современный.</text>
		<arg f="loc" n="m">на страницах которого</arg>
		<rel f="">сошлись</rel>
		<arg f="" n="0">роман классический и современный</arg>
	  </example>
	  <example name="gathered" src="Russian National Corpus [Сати Спивакова. Не всё (2002)]" type="">
        <text>Так сложилось, что в Большом зале сошлось множество официальных лиц ― в партере одновременно сидели Наина Иосифовна Ельцина, Чубайс, Лужков со всей своей командой из мэрии.</text>
		<arg f="loc" n="m">в Большом зале</arg>
		<rel f="">сошлось</rel>
		<arg f="" n="0">множество официальных лиц</arg>
	  </example>
	  <example name="reflexive as middle" src="Russian National Corpus [Наталья Дубова. Вокруг ITSM // «Computerworld», 2004] " type="">
        <text>компании "Крок"" Ай-Теко", Tops BI, IBS, BAC "Открытые технологии", Inline Group), сходились на том, что большинство проектов в нашей стране пока не выходят за рамки реализации оперативных процессов управления ИТ-услугами.</text>
		<arg f="" n="0">компании "Крок"" Ай-Теко", Tops BI, IBS, BAC "Открытые технологии", Inline Group)</arg>
		<rel f="">сходились</rel>
		<arg f="" n="2">на том, что большинство проектов в нашей стране пока не выходят за рамки реализации оперативных процессов управления ИТ-услугами</arg>
	  </example>
	  <example name="agree" src="Russian National Corpus [Александр Волков. Одеться с иголочки и без ниточки // «Знание -- сила», 2003] " type="">
        <text>Специалисты сходятся во мнении, что в "одежду будущего" должны быть встроены три жизненно важных прибора - мобильный телефон, навигационная система и компьютер.</text>
		<arg f="" n="o">Специалисты</arg>
		<rel f="">сходятся</rel>
		<arg f="" n="2">во мнении, что в "одежду будущего" должны быть встроены три жизненно важных прибора - мобильный телефон, навигационная система и компьютер</arg>
	  </example>
	  <example name="be consistent" src="Russian National Corpus[Иван-дурак и миллиардер Шахновский (2003) // «Завтра», 2003.08.22]" type="">
        <text>Чтобы всё "сходилось", нефтяники делают их "невидимыми".<text>
		<rel f="">сходилось</rel>
		<arg f="" n="o">всё</arg>
	  </example>
	  <example name="jibe well" src="Russian National Corpus [Дмитрий Кувичка. Нет больше сил смотреть на солнце. Раскрыт секрет успеха отечественных «пляжников» (2001) // «Известия», 2001.09.30]" type="">
        <text>Не сходятся характерами, думают, что если не получается добиться результата сразу, надо менять партнёра.</text>
		<arg f="neg" n="m">Не</arg>
		<rel f="">сходятся</rel>
		<arg f="" n="2">характерами</arg>
	  </example>
	  <example name="fight" src="Russian National Corpus [Криминальное досье (2003) // «Марийская правда» (Йошкар-Ола), 2003.01.14]" type="">
        <text>ПОЗДНО ночью в деревне Луначарка Горномарийского района сошлись в смертной драке два брата.</text>
		<arg f="tmp" n="m">ПОЗДНО ночью</arg>
		<arg f="loc" n="m">в деревне Луначарка Горномарийского района</arg>
		<rel f="">сошлись</rel>
		<arg f="" n="2">в смертной драке</arg>
		<arg f="" n="o">два брата</arg>
	  </example>
	 </roleset>
	
	<roleset id="сойтись.08" name="get close with someone, befriend, shack up"/>
		<aliases>
	  <alias framenet="" pos="v" verbnet="">сходиться</alias>
      </aliases>
	  <note>сойти.04 NOTES:Roleset based on English verb frame close.13</note>
	  <note>Corresponds to FrameBank sense -ся 7</note>
      <roles>
		<role descr="affectionate entity/ies" f="PAG" n="1"/>
		<role descr="affectionate with whom?" f="COM" n="2"/>
	  </roles>
	  <example name="" src="Russian National Corpus [Василий Катанян. Лиля Брик. Жизнь (1999)]" type="">
        <text>Еще до революции молодой Маяковский близко сошелся с Осипом Бриком.</text>
		<arg f="tmp" n="m">Еще до революции</arg>
		<arg f="" n="1">молодой Маяковский</arg>
		<arg f="adv" n="m">близко</arg>
		<rel f="">сошелся</rel>
		<arg f="" n="2">с Осипом Бриком</arg>
	  </example>
	  <example name="shack up" src="Russian National Corpus [Асар Эппель. В паровозные годы // «Знамя», 2002]" type="">
        <text>Вот Соня Дозе, образованная девушка, а сошлась с шофером и живет с ним как с мужем.</text>
		<rel f="">сошлась</rel>
		<arg f="" n="1">с шофером</arg>
	  </example>
	</roleset>
  </predicate>
	  
  <predicate lemma="сойти_с_ума">
    <roleset id="сойти_с_ума-m" name="be/go crazy, out of one's mind">
      <aliases>
	  </aliases>
		<mwe id="сойти_с_ума">
			<token slot="A" arg="" pos="" head="" dep="">сойти</token>
			<token slot="B" arg="" pos="" head="C" dep="">с</token>
			<token slot="C" arg="" pos="" head="A" dep="">ума</token>
		</mwe>
      </aliases>
      <note>сойти_с_ума NOTES: Based on English frame suspect.01</note>
      <roles>
		<role descr="lunatic" f="PPT" n="1"/>
      </roles>
      <example name="example" src="Russian National Corpus [Наши дети: Подростки (2004)]" type="">
        <text>Девченки по нему с ума сойдут: -)</text>
		<arg f="" n="1">Девченки</arg>
		<arg f="cau" n="m">по нему</arg>
		<rel f="">с</rel>
		<rel f="">ума</rel>
		<rel f="">сойдут</rel>
      </example>
	</roleset>
  </predicate>
</frameset>
  
